{
  "generatedAt": "2026-07-21T01:20:51.437Z",
  "totalAccounts": 9057,
  "accountsWithPositions": 1507,
  "byOI": [
    {
      "account": "0x228e195eb98faa456b17c2d285495a3bee22765e",
      "oi": 0,
      "uPnl": 0,
      "volume": 0,
      "positionCount": 0,
      "top": null
    },
    {
      "account": "0x5e6170e592b94cbe7c90cb453c3ded1ae913d437",
      "oi": 0,
      "uPnl": 0,
      "volume": 0,
      "positionCount": 0,
      "top": null
    },
    {
      "account": "0xd546fca46b5219d8f7b6c2fa9ca722944deb30bd",
      "oi": 0,
      "uPnl": 0,
      "volume": 381796.4680433,
      "positionCount": 0,
      "top": null
    },
    {
      "account": "0x81ba93b26bce8ca5d649b6607df15e6d45462d8f",
      "oi": 0,
      "uPnl": -10983.381813,
      "volume": 26933.014733,
      "positionCount": 1,
      "top": {
        "symbol": "#1",
        "side": "long",
        "lev": 10,
        "notional": 0
      }
    },
    {
      "account": "0x38c2d9a73bfb23972c91af9c9f91e6d20f58ca18",
      "oi": 0,
      "uPnl": -989.9915930000001,
      "volume": 989.991593,
      "positionCount": 1,
      "top": {
        "symbol": "#1",
        "side": "long",
        "lev": 2,
        "notional": 0
      }
    },
    {
      "account": "0xafbe47c7366270d546a04e65029f071ffc4a7e92",
      "oi": 0,
      "uPnl": 0,
      "volume": 0,
      "positionCount": 0,
      "top": null
    },
    {
      "account": "0x0ba3c0eeffa41ecc81efbb6c94725eeeb628cab7",
      "oi": 0,
      "uPnl": 0,
      "volume": 0,
      "positionCount": 0,
      "top": null
    },
    {
      "account": "0x9613eca44f5e6b3045284537a6ba4b56ba0e7ca8",
      "oi": 0,
      "uPnl": 0,
      "volume": 9297.4217969,
      "positionCount": 0,
      "top": null
    },
    {
      "account": "0xc61799ece0d9dcea0eef8075b445922a074c8cd4",
      "oi": 0,
      "uPnl": 0,
      "volume": 0,
      "positionCount": 0,
      "top": null
    },
    {
      "account": "0x6d0f80ad188e93cefdd72f8d0f38c78126697a6f",
      "oi": 0,
      "uPnl": 991.875,
      "volume": 991.875,
      "positionCount": 1,
      "top": {
        "symbol": "#5",
        "side": "short",
        "lev": 2,
        "notional": 0
      }
    },
    {
      "account": "0x006642e1bf48a96903952b9d0f10e379a0e9170a",
      "oi": 0,
      "uPnl": -7.123290856524704,
      "volume": 23427.94993220001,
      "positionCount": 4,
      "top": {
        "symbol": "#1",
        "side": "short",
        "lev": 20,
        "notional": 0
      }
    },
    {
      "account": "0x241df84bf413509967d8f1c98588907ef40bfb7d",
      "oi": 0,
      "uPnl": 0,
      "volume": 0,
      "positionCount": 0,
      "top": null
    },
    {
      "account": "0x6f6dd59747f78e6b2b64df63e0cdeb79f0e462e4",
      "oi": 0,
      "uPnl": 0,
      "volume": 0,
      "positionCount": 0,
      "top": null
    },
    {
      "account": "0x0ba866fdbceccd5658833ec36da4bd83065e76bb",
      "oi": 0,
      "uPnl": -5014.848,
      "volume": 15029.39136,
      "positionCount": 1,
      "top": {
        "symbol": "#1",
        "side": "long",
        "lev": 25,
        "notional": 0
      }
    },
    {
      "account": "0xd1a4e582f56b15868c89e453765bba81f2afe96b",
      "oi": 0,
      "uPnl": -22.3778002,
      "volume": 262.08097549999997,
      "positionCount": 1,
      "top": {
        "symbol": "#1",
        "side": "long",
        "lev": 25,
        "notional": 0
      }
    },
    {
      "account": "0xeea5712b60dac992f9217cc00c062c00eb913921",
      "oi": 0,
      "uPnl": 0,
      "volume": 49884.911403200014,
      "positionCount": 0,
      "top": null
    },
    {
      "account": "0xdfe880fec4b99fe554457f86f6709b7e94ce4b37",
      "oi": 0,
      "uPnl": 0,
      "volume": 0,
      "positionCount": 0,
      "top": null
    },
    {
      "account": "0x3208da70f0a85f862602593a22e3502ccb3abdde",
      "oi": 0,
      "uPnl": -2201.151017,
      "volume": 11345.007755,
      "positionCount": 1,
      "top": {
        "symbol": "#4",
        "side": "long",
        "lev": 10,
        "notional": 0
      }
    },
    {
      "account": "0xaca27c2745a287f62aec45230bd6db6a9b5cd3b6",
      "oi": 0,
      "uPnl": 2499.900705,
      "volume": 5688.283616,
      "positionCount": 2,
      "top": {
        "symbol": "#11",
        "side": "short",
        "lev": 3,
        "notional": 0
      }
    },
    {
      "account": "0x34e7b42efa18ab64e9f479205b13dfd91ab87870",
      "oi": 0,
      "uPnl": 0,
      "volume": 12118.571958499997,
      "positionCount": 0,
      "top": null
    }
  ],
  "byUpnl": [
    {
      "account": "0x7c6bf9003ae3ba366883f63a28c4f3fd6a5958a0",
      "oi": 0,
      "uPnl": 482349.36709899997,
      "volume": 238959.5398037,
      "positionCount": 5,
      "top": {
        "symbol": "#8",
        "side": "short",
        "lev": 10,
        "notional": 0
      }
    },
    {
      "account": "0x2f69b0561eb3dc323c9ae7fc671c9b189171310e",
      "oi": 0,
      "uPnl": 403815.3273286,
      "volume": 167167.08743,
      "positionCount": 2,
      "top": {
        "symbol": "#1",
        "side": "short",
        "lev": 25,
        "notional": 0
      }
    },
    {
      "account": "0x123f1c8d9f49bba27083e3b1510bdb0a2cad4919",
      "oi": 0,
      "uPnl": 337893.42480375,
      "volume": 4014.52,
      "positionCount": 5,
      "top": {
        "symbol": "#1",
        "side": "short",
        "lev": 25,
        "notional": 0
      }
    },
    {
      "account": "0xabbc45d1726e3231e6fbad61eb72aef71b035787",
      "oi": 0,
      "uPnl": 317890.30064156494,
      "volume": 400775.5883029999,
      "positionCount": 6,
      "top": {
        "symbol": "#1",
        "side": "short",
        "lev": 25,
        "notional": 0
      }
    },
    {
      "account": "0xd1f86f3c3e14aa992cafb6941e3b6410fde77aa2",
      "oi": 0,
      "uPnl": 244665.3470539736,
      "volume": 732393.638863,
      "positionCount": 1,
      "top": {
        "symbol": "#1",
        "side": "short",
        "lev": 15,
        "notional": 0
      }
    },
    {
      "account": "0x1b490dfc0893368e9bfdfce73d6ef6198329ebed",
      "oi": 0,
      "uPnl": 167578.03147,
      "volume": 0,
      "positionCount": 2,
      "top": {
        "symbol": "#5",
        "side": "short",
        "lev": 20,
        "notional": 0
      }
    },
    {
      "account": "0xf75c80c791e161aff4aec2109a3aed6ec8dfecb5",
      "oi": 0,
      "uPnl": 130855.30435161653,
      "volume": 0,
      "positionCount": 2,
      "top": {
        "symbol": "#1",
        "side": "short",
        "lev": 25,
        "notional": 0
      }
    },
    {
      "account": "0xe50681d35ba91c5b13412ad2ea5f34b94141b122",
      "oi": 0,
      "uPnl": 128680,
      "volume": 128680.00000000003,
      "positionCount": 1,
      "top": {
        "symbol": "#1",
        "side": "short",
        "lev": 25,
        "notional": 0
      }
    },
    {
      "account": "0x6c538c89739e7d5e15846fafd338533a4dddca14",
      "oi": 0,
      "uPnl": 125131.21798,
      "volume": 0,
      "positionCount": 2,
      "top": {
        "symbol": "#5",
        "side": "short",
        "lev": 10,
        "notional": 0
      }
    },
    {
      "account": "0x69be108a2aaa3e06df75f854df08d215acf0ca7a",
      "oi": 0,
      "uPnl": 89920.56905,
      "volume": 0,
      "positionCount": 3,
      "top": {
        "symbol": "#2",
        "side": "short",
        "lev": 25,
        "notional": 0
      }
    },
    {
      "account": "0x4a9488252f6be406aeca028760e5b6385b3766fe",
      "oi": 0,
      "uPnl": 78005.88747,
      "volume": 120236.12208999998,
      "positionCount": 1,
      "top": {
        "symbol": "#5",
        "side": "short",
        "lev": 10,
        "notional": 0
      }
    },
    {
      "account": "0x4a07a7c6fe412d14134dce2bb738b32757b968fe",
      "oi": 0,
      "uPnl": 77491.58282899999,
      "volume": 77491.582829,
      "positionCount": 1,
      "top": {
        "symbol": "#1",
        "side": "short",
        "lev": 20,
        "notional": 0
      }
    },
    {
      "account": "0xec40a926bb1175b6c17c5d67f9c314e6fa75d414",
      "oi": 0,
      "uPnl": 58903.79923,
      "volume": 0,
      "positionCount": 1,
      "top": {
        "symbol": "#5",
        "side": "short",
        "lev": 20,
        "notional": 0
      }
    },
    {
      "account": "0x69fa9ebb4bc4fcecdd641d5162fe69ed22617bff",
      "oi": 0,
      "uPnl": 53264.78509,
      "volume": 245069.70460699988,
      "positionCount": 1,
      "top": {
        "symbol": "#8",
        "side": "short",
        "lev": 10,
        "notional": 0
      }
    },
    {
      "account": "0x88ddcca720ce1688c65051054f2b4d4ed8fa49e6",
      "oi": 0,
      "uPnl": 44992.759198,
      "volume": 0,
      "positionCount": 2,
      "top": {
        "symbol": "#5",
        "side": "short",
        "lev": 20,
        "notional": 0
      }
    },
    {
      "account": "0xc473eee5ff7218d5831d2d969950eb78f386f5a4",
      "oi": 0,
      "uPnl": 44765,
      "volume": 0,
      "positionCount": 1,
      "top": {
        "symbol": "#1",
        "side": "short",
        "lev": 25,
        "notional": 0
      }
    },
    {
      "account": "0xc5a33ea364fe008c88ee7c064a6ff0a251cb6cd6",
      "oi": 0,
      "uPnl": 40776.501577995805,
      "volume": 8678.989707400002,
      "positionCount": 8,
      "top": {
        "symbol": "#1",
        "side": "short",
        "lev": 25,
        "notional": 0
      }
    },
    {
      "account": "0x5f7227098ecf97ebe84b615bfd9d797cc8d5dcc7",
      "oi": 0,
      "uPnl": 39983.499173,
      "volume": 285087.75747999985,
      "positionCount": 1,
      "top": {
        "symbol": "#17",
        "side": "short",
        "lev": 20,
        "notional": 0
      }
    },
    {
      "account": "0x5de2f45bb23180f49762dbafee319a4987651f50",
      "oi": 0,
      "uPnl": 38514.344200499996,
      "volume": 55846.808787099995,
      "positionCount": 1,
      "top": {
        "symbol": "#1",
        "side": "short",
        "lev": 5,
        "notional": 0
      }
    },
    {
      "account": "0x09a84271d2db092de1726a239b653223dd9f3a00",
      "oi": 0,
      "uPnl": 37142.87607536705,
      "volume": 88263.121517,
      "positionCount": 3,
      "top": {
        "symbol": "#1",
        "side": "long",
        "lev": 10,
        "notional": 0
      }
    }
  ],
  "byVolume": [
    {
      "account": "0x0b126048f6b44681e31bb05407c13f9fbaeb0bf5",
      "oi": 0,
      "uPnl": 0,
      "volume": 1074702.7928446995,
      "positionCount": 0,
      "top": null
    },
    {
      "account": "0x85bb3359a4d2ae8c4ce1ce2bf09ac35bfe224b9c",
      "oi": 0,
      "uPnl": -132389.44899119998,
      "volume": 869583.0582459001,
      "positionCount": 1,
      "top": {
        "symbol": "#1",
        "side": "long",
        "lev": 25,
        "notional": 0
      }
    },
    {
      "account": "0xd1f86f3c3e14aa992cafb6941e3b6410fde77aa2",
      "oi": 0,
      "uPnl": 244665.3470539736,
      "volume": 732393.638863,
      "positionCount": 1,
      "top": {
        "symbol": "#1",
        "side": "short",
        "lev": 15,
        "notional": 0
      }
    },
    {
      "account": "0x679fb6c74b531e3f3136decbe9238cec6029f59a",
      "oi": 0,
      "uPnl": 1555.065148699996,
      "volume": 679037.8199838,
      "positionCount": 2,
      "top": {
        "symbol": "#1",
        "side": "long",
        "lev": 25,
        "notional": 0
      }
    },
    {
      "account": "0x0a228af0e5885db249d87c469d6ebd3fcaddc0cf",
      "oi": 0,
      "uPnl": 18015.022009299995,
      "volume": 644775.1538072,
      "positionCount": 3,
      "top": {
        "symbol": "#1",
        "side": "long",
        "lev": 25,
        "notional": 0
      }
    },
    {
      "account": "0x966d9ccde9ff8fd0ba04c1df2dde96f2cf1d92ec",
      "oi": 0,
      "uPnl": 36169.8639557,
      "volume": 625215.9092306001,
      "positionCount": 2,
      "top": {
        "symbol": "#1",
        "side": "short",
        "lev": 10,
        "notional": 0
      }
    },
    {
      "account": "0x083d93758661649edaeaba40d7477a46b1098716",
      "oi": 0,
      "uPnl": -260380.1765115,
      "volume": 602719.5718137,
      "positionCount": 1,
      "top": {
        "symbol": "#1",
        "side": "long",
        "lev": 25,
        "notional": 0
      }
    },
    {
      "account": "0x2ffeef75f39a2d7cc12f7b11b1c5e351a4339f45",
      "oi": 0,
      "uPnl": -125727.38100000001,
      "volume": 499998.097561,
      "positionCount": 1,
      "top": {
        "symbol": "#2",
        "side": "long",
        "lev": 25,
        "notional": 0
      }
    },
    {
      "account": "0x909af897110e8e852113a7156d8e4ce76c268d86",
      "oi": 0,
      "uPnl": -900.394877,
      "volume": 485095.63498169964,
      "positionCount": 1,
      "top": {
        "symbol": "#17",
        "side": "long",
        "lev": 20,
        "notional": 0
      }
    },
    {
      "account": "0x0b83821bb8b9d19582af26122556be7408313140",
      "oi": 0,
      "uPnl": 0,
      "volume": 431735.0707792002,
      "positionCount": 0,
      "top": null
    },
    {
      "account": "0x0955ecdbe1fcf1fa2cbfad24af648c7a459f9fa2",
      "oi": 0,
      "uPnl": 12999.784770000002,
      "volume": 428155.1858237999,
      "positionCount": 1,
      "top": {
        "symbol": "#1",
        "side": "short",
        "lev": 2,
        "notional": 0
      }
    },
    {
      "account": "0x0fcbbc16fd3a3eeccbb363e89e7ba3e5d7f16aa4",
      "oi": 0,
      "uPnl": -3336.9803,
      "volume": 405851.15750239993,
      "positionCount": 1,
      "top": {
        "symbol": "#5",
        "side": "long",
        "lev": 5,
        "notional": 0
      }
    },
    {
      "account": "0xabbc45d1726e3231e6fbad61eb72aef71b035787",
      "oi": 0,
      "uPnl": 317890.30064156494,
      "volume": 400775.5883029999,
      "positionCount": 6,
      "top": {
        "symbol": "#1",
        "side": "short",
        "lev": 25,
        "notional": 0
      }
    },
    {
      "account": "0xd546fca46b5219d8f7b6c2fa9ca722944deb30bd",
      "oi": 0,
      "uPnl": 0,
      "volume": 381796.4680433,
      "positionCount": 0,
      "top": null
    },
    {
      "account": "0xa1cb5d81274fc05c5b5bb86761adf2500c51ed0b",
      "oi": 0,
      "uPnl": 0,
      "volume": 343956.82875359996,
      "positionCount": 0,
      "top": null
    },
    {
      "account": "0x3b60e6a4c40615194e6bf2b1f3220fcb910e0516",
      "oi": 0,
      "uPnl": 1099.9503679999998,
      "volume": 327007.28723170003,
      "positionCount": 3,
      "top": {
        "symbol": "#10",
        "side": "long",
        "lev": 10,
        "notional": 0
      }
    },
    {
      "account": "0x938a104179a2d23dec249a968ecd5b4f8b857cac",
      "oi": 0,
      "uPnl": -25029.72620503912,
      "volume": 303766.2261238,
      "positionCount": 14,
      "top": {
        "symbol": "#1",
        "side": "long",
        "lev": 25,
        "notional": 0
      }
    },
    {
      "account": "0x777f066fef288208128dd99e9f06ae26c2a3312e",
      "oi": 0,
      "uPnl": -6003.89483,
      "volume": 302807.9840575001,
      "positionCount": 1,
      "top": {
        "symbol": "#7",
        "side": "long",
        "lev": 3,
        "notional": 0
      }
    },
    {
      "account": "0x2346a596c53699e50fffd54fefc484e1854e7ec3",
      "oi": 0,
      "uPnl": 0,
      "volume": 301621.0932246,
      "positionCount": 0,
      "top": null
    },
    {
      "account": "0x346a260b82ee8f7f12b9a42d52266b5b9b7e4ee3",
      "oi": 0,
      "uPnl": 19699.2317309,
      "volume": 288512.59118280007,
      "positionCount": 1,
      "top": {
        "symbol": "#1",
        "side": "short",
        "lev": 20,
        "notional": 0
      }
    }
  ]
}